br4nch/__init__.py
br4nch/create/__init__.py
br4nch/create/create_node.py
br4nch/create/create_tree.py
br4nch/delete/__init__.py
br4nch/delete/delete_node.py
br4nch/delete/delete_tree.py
br4nch/display/__init__.py
br4nch/display/display_assist.py
br4nch/display/display_tree.py
br4nch/duplicate/__init__.py
br4nch/duplicate/duplicate_node.py
br4nch/duplicate/duplicate_tree.py
br4nch/export/__init__.py
br4nch/export/export_json.py
br4nch/export/export_text.py
br4nch/export/export_tree.py
br4nch/filter/__init__.py
br4nch/filter/filter_node.py
br4nch/get/__init__.py
br4nch/get/get_data.py
br4nch/get/get_node.py
br4nch/get/get_position.py
br4nch/get/get_tree.py
br4nch/load/__init__.py
br4nch/load/load_folder.py
br4nch/load/load_json.py
br4nch/load/load_tree.py
br4nch/move/__init__.py
br4nch/move/move_node.py
br4nch/replace/__init__.py
br4nch/replace/replace_header.py
br4nch/replace/replace_node.py
br4nch/replace/replace_tree.py
br4nch/reset/__init__.py
br4nch/reset/reset_size.py
br4nch/reset/reset_symbol.py
br4nch/set/__init__.py
br4nch/set/set_size.py
br4nch/set/set_symbol.py
br4nch/utility/__init__.py
br4nch/utility/utility_builder.py
br4nch/utility/utility_decider.py
br4nch/utility/utility_generator.py
br4nch/utility/utility_handler.py
br4nch/utility/utility_librarian.py
br4nch-2.4.dist-info/LICENSE
br4nch-2.4.dist-info/METADATA
br4nch-2.4.dist-info/WHEEL
br4nch-2.4.dist-info/top_level.txt
br4nch-2.4.dist-info/RECORD
