Metadata-Version: 2.1
Name: br4nch
Version: 2.4
Summary: Data Structure Tree Builder for Python.
Home-page: https://github.com/TRSTN4/br4nch
Author: TRSTN4
Author-email: <tristan@trstn4.com>
License: GNU General Public License v3.0
Download-URL: https://github.com/TRSTN4/br4nch/archive/refs/tags/2.4.tar.gz
Keywords: br4nch,python,python3,data,structure,tree,builder,generate,algorithm
Platform: UNKNOWN
Classifier: Intended Audience :: Developers
Classifier: Development Status :: 5 - Production/Stable
Classifier: Programming Language :: Python :: 3.10
Classifier: Programming Language :: Python :: 3.9
Classifier: Programming Language :: Python :: 3.8
Classifier: Programming Language :: Python :: 3.7
Requires-Python: >=3.7
License-File: LICENSE
